opthub_runner_admin/__init__.py
opthub_runner_admin/args.py
opthub_runner_admin/environments.py
opthub_runner_admin/evaluator/__init__.py
opthub_runner_admin/evaluator/main.py
opthub_runner_admin/lib/__init__.py
opthub_runner_admin/lib/appsync.py
opthub_runner_admin/lib/docker_executor.py
opthub_runner_admin/lib/dynamodb.py
opthub_runner_admin/lib/sqs.py
opthub_runner_admin/main.py
opthub_runner_admin/models/__init__.py
opthub_runner_admin/models/evaluation.py
opthub_runner_admin/models/exception.py
opthub_runner_admin/models/match.py
opthub_runner_admin/models/schema.py
opthub_runner_admin/models/score.py
opthub_runner_admin/models/solution.py
opthub_runner_admin/scorer/__init__.py
opthub_runner_admin/scorer/cache.py
opthub_runner_admin/scorer/history.py
opthub_runner_admin/scorer/main.py
opthub_runner_admin/utils/__init__.py
opthub_runner_admin/utils/converter.py
opthub_runner_admin/utils/credentials/__init__.py
opthub_runner_admin/utils/credentials/cipher_suite.py
opthub_runner_admin/utils/credentials/credentials.py
opthub_runner_admin/utils/dir.py
opthub_runner_admin/utils/docker.py
opthub_runner_admin/utils/process.py
opthub_runner_admin/utils/time.py
opthub_runner_admin/utils/truncate.py
opthub_runner_admin/utils/zfill.py
opthub_runner_admin-0.4.4.dist-info/LICENSE
opthub_runner_admin-0.4.4.dist-info/METADATA
opthub_runner_admin-0.4.4.dist-info/WHEEL
opthub_runner_admin-0.4.4.dist-info/entry_points.txt
opthub_runner_admin-0.4.4.dist-info/RECORD
