Metadata-Version: 2.1
Name: opthub_runner_admin
Version: 0.4.4
Summary: Library for running OptHub problems and indicators.
Home-page: https://github.com/opthub-org/opthub-runner-admin
License: MIT
Keywords: opthub,runner,evaluator,scorer
Author: Opthub Inc.
Author-email: dev@opthub.ai
Requires-Python: >=3.10,<4.0
Classifier: License :: OSI Approved :: MIT License
Classifier: Programming Language :: Python :: 3
Classifier: Programming Language :: Python :: 3.10
Classifier: Programming Language :: Python :: 3.11
Classifier: Programming Language :: Python :: 3.12
Requires-Dist: PyYAML (>=6.0,<7.0)
Requires-Dist: aiohttp (>=3.9.3,<4.0.0)
Requires-Dist: boto3 (>=1.34,<2.0)
Requires-Dist: click (>=8.1.7,<9.0.0)
Requires-Dist: cryptography (>=42.0.7,<43.0.0)
Requires-Dist: docker (>=7.1.0,<8.0.0)
Requires-Dist: filelock (>=3.16.1,<4.0.0)
Requires-Dist: gql (>=3.5.0,<4.0.0)
Requires-Dist: jwcrypto (>=1.5.6,<2.0.0)
Requires-Dist: pyjwt (>=2.8.0,<3.0.0)
Requires-Dist: requests (>=2.31.0,<3.0.0)
Project-URL: Documentation, https://github.com/opthub-org/opthub-runner-admin
Project-URL: Repository, https://github.com/opthub-org/opthub-runner-admin
